{
  "review_count": 96,
  "reviews": [
    {
      "reviewId": "bd2b9f21-2e0f-4a9e-9ffe-adce2029631d",
      "rating": 5,
      "review_text": "Good broker , but sometimes facing Laging issue",
      "review_date": "2026-03-14 02:00:04"
    },
    {
      "reviewId": "a7157823-6d0e-4f60-810c-8573adfea41d",
      "rating": 3,
      "review_text": "too much charges",
      "review_date": "2026-03-14 00:23:24"
    },
    {
      "reviewId": "00cf9742-5a0f-4aec-8c9c-1f95811abd70",
      "rating": 5,
      "review_text": "I am using this app for the last 2 years. It is verry good investment app. I want to know if there are any possibilities to know the buy/sale signal for bullish/bearish trend of Indian stock?",
      "review_date": "2026-03-14 00:21:45"
    },
    {
      "reviewId": "07107dca-d235-4296-a3fe-8f1075dec379",
      "rating": 1,
      "review_text": "app me 24/7 call dikha rahe 10min wait karo kuch bhi response nahi milega grow team ke sath chat karo vo bol rahe humari senior team aapko call karnge abhi tak kuch nahi 😡",
      "review_date": "2026-03-14 00:09:51"
    },
    {
      "reviewId": "81f58d8c-b25c-4744-8334-610a0fa98787",
      "rating": 5,
      "review_text": "Excellent app for the first time investor.",
      "review_date": "2026-03-13 23:32:51"
    },
    {
      "reviewId": "3e701a41-d745-403e-99ee-be03cf4c4bf0",
      "rating": 4,
      "review_text": "good but need to improve user friendly and need to help investor or trader",
      "review_date": "2026-03-13 22:55:30"
    },
    {
      "reviewId": "a179b426-4c68-4427-ad3d-bd8b5bb8fe58",
      "rating": 3,
      "review_text": "the best ui broker app for stocks and mutual funds but there is no SWP option for the mutual funds so its a big drawback of this app i want to know the option",
      "review_date": "2026-03-13 21:26:12"
    },
    {
      "reviewId": "a9320e37-2282-49be-bcf8-e2cd2195ce63",
      "rating": 1,
      "review_text": "buy= 20 rupees charge + gst. sell= 20 rupees charge + gst. 40 rupees+gst on every trade is too expensive. don't do treding on this app. download shoonya app it's free,no brokerage charges or gst on it.you can save upto 50 rupees per trade.",
      "review_date": "2026-03-13 21:07:36"
    },
    {
      "reviewId": "67f560a0-2c79-4ccd-9350-b0258d3c3c9e",
      "rating": 5,
      "review_text": "Sera EG share market app",
      "review_date": "2026-03-13 19:42:51"
    },
    {
      "reviewId": "815fdf58-87a2-481d-a22b-2529579cf93c",
      "rating": 1,
      "review_text": "very poor and pathetic app.i hve given the request to activation of commodity section bt till now there is no revert from Groww side.i have talked to customer care also several times bt no +ve response.Pl don't download this app.no service no customer attention.",
      "review_date": "2026-03-13 18:41:42"
    },
    {
      "reviewId": "9bc55c81-e4d2-4816-8884-e4fbecfbeb6a",
      "rating": 5,
      "review_text": "This app is best for beginners User friendly interface. The only one issue I was facing since last update is that the full landscape chart display can't work properly. it's load and then suddenly open the home screen 😭😂👍👍 The most impressive thing is that the charges are really minimum. As compared to other apps. 😎🙂..Keep Growing with Groww .🇮🇳",
      "review_date": "2026-03-13 18:37:53"
    },
    {
      "reviewId": "f0f84aa5-2ca9-483a-ae1e-d25b2d0ec121",
      "rating": 1,
      "review_text": "mutual funds are not updating",
      "review_date": "2026-03-13 18:13:24"
    },
    {
      "reviewId": "e2e43cc0-4937-4778-8553-afcf54add579",
      "rating": 1,
      "review_text": "app good.. but brokrge charges high",
      "review_date": "2026-03-13 15:38:31"
    },
    {
      "reviewId": "2c243dbb-25e4-46cc-a742-1d0f39324dd3",
      "rating": 5,
      "review_text": "very nice but vwap is not show why ?",
      "review_date": "2026-03-13 15:31:59"
    },
    {
      "reviewId": "fd46f840-6250-41db-980c-67ba65084a81",
      "rating": 1,
      "review_text": "fake Costmar sarvice fake tele support heavy charges",
      "review_date": "2026-03-13 14:15:50"
    },
    {
      "reviewId": "78b19861-f480-43a5-8ddb-35fd3104a822",
      "rating": 1,
      "review_text": "“The service is good, but the charges are too high. It would be better if the fees were reduced.”",
      "review_date": "2026-03-13 14:09:16"
    },
    {
      "reviewId": "46b5a2c9-0a4d-4e5c-badf-a5b5a0864129",
      "rating": 1,
      "review_text": "Not a reliable app for trading because of discrepancies/delays encountered during selling & buying stocks. Also high external charges & taxes charged by Groww apart from their brokerage charges.",
      "review_date": "2026-03-13 12:57:24"
    },
    {
      "reviewId": "29b32a7e-1e29-46e0-9a5f-4fa6a6afcbee",
      "rating": 2,
      "review_text": "add the technical support & resistance to nifty 50 chart in app like individual stocks are having. add all bse indices in Indian indices",
      "review_date": "2026-03-13 12:52:26"
    },
    {
      "reviewId": "433814f2-76f4-4421-9dae-9e39cf2f93dc",
      "rating": 3,
      "review_text": "The platform works well, but there is one issue that needs improvement. When placing an order, the TP (Take Profit) and SL (Stop Loss) are not set automatically, and it becomes difficult to add them manually from the position panel. It would be very helpful if you could introduce a drag-and-drop feature for TP and SL directly on the chart. This feature would make trading much faster and easier, not only for me but for many other users as well. Please consider adding this in a future update.",
      "review_date": "2026-03-13 11:45:18"
    },
    {
      "reviewId": "92034f9d-a6ec-4630-8979-527b61aa027d",
      "rating": 1,
      "review_text": "chrj bhut jada hai bad customer service",
      "review_date": "2026-03-13 10:59:46"
    },
    {
      "reviewId": "fae1405a-7f31-49a6-a732-7080e2ea5d7b",
      "rating": 1,
      "review_text": "Grow par bahut dino se external funds update nahi ho rhe dusre sabi apps par fund update ho rhe hain grow ko be update jaldi deni chahiye ta ke hum aap ne external funds ko grow par track kar ske",
      "review_date": "2026-03-13 10:34:14"
    },
    {
      "reviewId": "c82aced1-062d-4120-aed2-a561a26e443c",
      "rating": 5,
      "review_text": "This app is beginner friendly and i am trading first time in my life and bcz of this app it is easy as pie 🥧...",
      "review_date": "2026-03-13 10:23:08"
    },
    {
      "reviewId": "05f3f999-1c79-4ca8-b2b7-76b1f91ef08e",
      "rating": 5,
      "review_text": "very good sip 😊",
      "review_date": "2026-03-13 08:30:40"
    },
    {
      "reviewId": "125260f4-1f15-4b23-bada-3402ea55ae7e",
      "rating": 5,
      "review_text": "good app for stock market",
      "review_date": "2026-03-13 08:21:42"
    },
    {
      "reviewId": "3ed0217e-89bd-4e6d-977d-0c95ad712987",
      "rating": 3,
      "review_text": "GTT not working , Automatically deleted orders next day morning, I losses so many opportunities 😭",
      "review_date": "2026-03-13 08:16:11"
    },
    {
      "reviewId": "b361b08d-d4f7-4ea5-a138-f203c361b665",
      "rating": 2,
      "review_text": "External fund tracking in MF section is not working for a while. Why? Is this a bug? Also under Stock section, in Holding tab when trying to track external portfolios, that is also not working as expected. The external portfolios are not getting fetched. This is causing problems. Please resolve.",
      "review_date": "2026-03-13 02:46:32"
    },
    {
      "reviewId": "d642657c-4f74-4411-85ff-40db84325508",
      "rating": 1,
      "review_text": "if you exit art any amount like 58 market touch 60 and a nb down @55 grow always exit you in lower price everyday I am notices but no cc reply on it that no glitches it he have contact with big bang sellar its scam but no one able to expose",
      "review_date": "2026-03-13 01:29:00"
    },
    {
      "reviewId": "4eca4ccb-9f5f-4b7e-999a-5455621da7a0",
      "rating": 5,
      "review_text": "user friendly Requesting in next update the stop-loss and target must be set by % (percentage) when we buy at market price.",
      "review_date": "2026-03-12 23:03:39"
    },
    {
      "reviewId": "833df354-1623-44e3-9370-df853f7ad5a3",
      "rating": 2,
      "review_text": "first the watchlist is weird. second nowadays when modifying order from limit to market, it says no modification made so deactivates the trade button. it's frustrating i have to first edit the price even though i was a market order. change of order type is also a modication. please change it back. and why do you not have freeze in fno pause? i can activate it immediately. no point.",
      "review_date": "2026-03-12 22:53:37"
    },
    {
      "reviewId": "4d3dd201-39be-45d7-a723-536d9f32ce18",
      "rating": 1,
      "review_text": "this Company is a scam and they will also involve the government on the scam experience invest 33k profit booked 1k, this company charged me 1.5k brokerage and 1.5k government regulator charges, and other tax 1.5 k total collected 4.5K for getting benefit of 1k reason : buying or selling F&O each time 20rs. and tax this company is a fraud please don't use it they will make us to wait when we try to talk with customer care at least for 15mins",
      "review_date": "2026-03-12 22:34:46"
    },
    {
      "reviewId": "519cb791-44c3-4be2-a149-8951e2ac305f",
      "rating": 1,
      "review_text": "bohut bekar hai ye pese kat jate hai bank se bekar hai",
      "review_date": "2026-03-12 22:10:21"
    },
    {
      "reviewId": "9fac461a-f6d9-44e6-87c3-e631d99a51e3",
      "rating": 1,
      "review_text": "Groww trading app gives very misleading notifications. When the market goes up, it sends notifications suggesting PUT, and when the market goes down, it sends CALL notifications. This confuses traders and can cause losses. It feels like the app is misleading investors and putting their money at risk. Very disappointing",
      "review_date": "2026-03-12 21:08:54"
    },
    {
      "reviewId": "68fc31f0-74dd-4201-9a47-d7c90d7267c1",
      "rating": 3,
      "review_text": "most of the time hang hoti hai... 650rs k loss pr exit Krna start Kiya thha... 3hr baad 7k loss pr exit hua 🙄",
      "review_date": "2026-03-12 20:20:15"
    },
    {
      "reviewId": "ed8d9c5a-93bc-4c11-b7bb-94de7fea378f",
      "rating": 1,
      "review_text": "fraud",
      "review_date": "2026-03-12 20:02:19"
    },
    {
      "reviewId": "a705adb1-9cd2-4f38-8323-a3206e02e9d5",
      "rating": 4,
      "review_text": "100% sell balance holding my",
      "review_date": "2026-03-12 19:52:00"
    },
    {
      "reviewId": "60f351c9-d850-4519-8995-a5009d3380ac",
      "rating": 4,
      "review_text": "The Best 💖 One I wOuLd say, but it deMands RandOM updates AfteR A COupLe Of days. That's why 4 ⭐s, PLease iMpROve it I'LL Review this COmMent !! ThaNKs #GROww 🔵🤍🟢 teaM 🙏🏻😊 • On 12.MaRCH.2026 ....... I'm heRe 🙋 Once Again But , The Last mentiOned issue hasn't ResOLved yet ........ 🤡",
      "review_date": "2026-03-12 19:35:14"
    },
    {
      "reviewId": "d8857f3f-6b87-4829-89d2-64f9a5c0353e",
      "rating": 5,
      "review_text": "Not charging Much Broker Amount rather than other App",
      "review_date": "2026-03-12 18:17:30"
    },
    {
      "reviewId": "98255ffd-a90f-464d-a53a-631811c55683",
      "rating": 4,
      "review_text": "Nice experience with the app. Portfolio tracking and stock buying process work smoothly.",
      "review_date": "2026-03-12 17:33:23"
    },
    {
      "reviewId": "e27da16b-782d-460f-9b8c-b27b91d137d4",
      "rating": 1,
      "review_text": "not showing update, and when order executed also not updating. showing app error when we buy 1 time that is taking double time . worst situation. when we contact customer care they are saying different answers . worst performance of app. and not even providing solutions to our problem. service also no1 worst.",
      "review_date": "2026-03-12 17:32:02"
    },
    {
      "reviewId": "3e94513f-99f7-4c13-bf0f-0b519805023e",
      "rating": 5,
      "review_text": "Smooth performance and simple layout. Investing in mutual funds and monitoring returns is very convenient.",
      "review_date": "2026-03-12 17:31:12"
    },
    {
      "reviewId": "57c142cd-b301-4f04-8b36-266f06ec4d3d",
      "rating": 4,
      "review_text": "Simple and easy to use app. Investing in stocks and mutual funds is smooth, and the interface is clean.",
      "review_date": "2026-03-12 17:02:42"
    },
    {
      "reviewId": "5fba51bd-85db-4f46-befd-a06752cfcbc7",
      "rating": 5,
      "review_text": "good for stock buying",
      "review_date": "2026-03-12 16:28:03"
    },
    {
      "reviewId": "fb5ceb13-eda8-4777-83eb-1f6325d83f60",
      "rating": 2,
      "review_text": "app me aapko call put ek hi strike price pr set hoti isme scalping feature me Alag alag strike price so hona chiye & stop-loss chart pr nhi lagta & trailing stoploss ka feature bhi nhi hai is scalping tab me",
      "review_date": "2026-03-12 16:10:01"
    },
    {
      "reviewId": "99a2ef5c-dd32-49b1-9496-1c73e7751e6c",
      "rating": 5,
      "review_text": "Bast apply for your time and please 🙏",
      "review_date": "2026-03-12 16:04:01"
    },
    {
      "reviewId": "329fe93b-6494-45f7-be25-fe63775a6605",
      "rating": 1,
      "review_text": "I faced a serious issue while trading in the F&O section today. I had almost recovered my loss and only around ₹800 was left. When I refreshed the Groww app, my order got executed automatically and my loss suddenly increased again. This created confusion during live trading. I request the team to check this issue and improve app stability, order execution clarity, and real-time updates so traders do not face such problems in fast market conditions. waste app 😡",
      "review_date": "2026-03-12 15:51:57"
    },
    {
      "reviewId": "5e4e7120-05d4-4fb5-9608-51f4deb12131",
      "rating": 5,
      "review_text": "want a comment section on every stock page",
      "review_date": "2026-03-12 15:12:12"
    },
    {
      "reviewId": "2b6711ad-8778-48eb-857f-408b85471010",
      "rating": 1,
      "review_text": "I do not understand what was the problem in my groww account whenever I buy call or put there was not working properly very disappointed not working properly 😕",
      "review_date": "2026-03-12 15:02:47"
    },
    {
      "reviewId": "b94e5cc4-4935-4f4f-94fd-b5353f25ce42",
      "rating": 5,
      "review_text": "plese every time same protection helped with yours....",
      "review_date": "2026-03-12 14:03:24"
    },
    {
      "reviewId": "55367082-ac2d-4e29-992f-fa8a811f8bd8",
      "rating": 3,
      "review_text": "help full app",
      "review_date": "2026-03-12 13:02:51"
    },
    {
      "reviewId": "882f744d-dc01-4b8f-9150-5a755f82ac95",
      "rating": 5,
      "review_text": "Very good app for trading and mutual fund sip",
      "review_date": "2026-03-12 12:58:53"
    },
    {
      "reviewId": "ae61a281-d451-4a82-8291-dfb189a1b65c",
      "rating": 1,
      "review_text": "Don't install this application feature and options ke liye sahi nahi hai buy limit kuchh set karo aur same price par buy ho jata hai Target TP cross hone ke baad bhi sell nahi hota hai very bad application",
      "review_date": "2026-03-12 11:22:21"
    },
    {
      "reviewId": "4c98a4ab-f0f0-41d7-afe6-94daa56382bb",
      "rating": 5,
      "review_text": "Please add lower Time frame like 30 second.",
      "review_date": "2026-03-12 11:08:20"
    },
    {
      "reviewId": "0a9620d8-e44d-41b3-9023-94a9381c2d4a",
      "rating": 5,
      "review_text": "good account management technology",
      "review_date": "2026-03-12 10:32:10"
    },
    {
      "reviewId": "9a0ac0a9-56e2-4e16-8afa-8a4dcc57b192",
      "rating": 5,
      "review_text": "This application is very easy to handle, user friendly, easy mode to understand about stock market, commodity & IPOs... I'm happy with you",
      "review_date": "2026-03-12 10:31:46"
    },
    {
      "reviewId": "1925e536-18ef-4691-813e-bc0cc30d0b86",
      "rating": 2,
      "review_text": "The app was working just fine when they disabled the feature that would let you export the external funds as well. By when can we expect the feature enablement? The dashboard has old data for the portfolio that really doesn't help to track my investments.",
      "review_date": "2026-03-12 10:20:16"
    },
    {
      "reviewId": "b04d4b23-5099-4468-8aa4-b8861dee48b6",
      "rating": 4,
      "review_text": "UI is best from peers. please implement SL order for MTF order.",
      "review_date": "2026-03-12 10:10:58"
    },
    {
      "reviewId": "cae18114-d3d9-41a0-9fb7-7f989bad5c90",
      "rating": 1,
      "review_text": "wrost app brokerage is so high than others",
      "review_date": "2026-03-12 10:10:06"
    },
    {
      "reviewId": "934e501f-bdce-4727-9268-bbbc290b3295",
      "rating": 4,
      "review_text": "add more options in \"Add Money\" like Credit/Debit Card",
      "review_date": "2026-03-12 10:08:30"
    },
    {
      "reviewId": "d109e297-829f-43a8-b55c-5f153fadbbfe",
      "rating": 1,
      "review_text": "Very poor, if you search for call or put option it will not show you near by expiry it will show you dec expiry, march last expiry, very poor support team, they will disconnect the call if you raise your issue.",
      "review_date": "2026-03-12 09:33:02"
    },
    {
      "reviewId": "9b9c1025-efd6-4de1-8dfc-6bf1837e467c",
      "rating": 1,
      "review_text": "Bekar app h trading time pr nhi deta h loading leta h time pe sell nhi hota h order. Graph achhe se nhi show karta h app khulne me bhi time leta h 😑",
      "review_date": "2026-03-12 09:11:22"
    },
    {
      "reviewId": "a6d86aca-3771-40b2-bd95-db31565a846c",
      "rating": 1,
      "review_text": "Refresh external fund is on hold now. I। switching to other app.",
      "review_date": "2026-03-12 08:20:37"
    },
    {
      "reviewId": "c339b99f-8622-40b9-82ba-89ae864efa97",
      "rating": 1,
      "review_text": "plz notice everyone very bad experience this app take hidden charges just calculate one time all your added fund and brokerage taxes and losses then also you get less money I faced a very very bad experience and from 2-3 days I am contacting the customer service but not got any satisfaction with my queries",
      "review_date": "2026-03-12 06:23:34"
    },
    {
      "reviewId": "ab5a89ec-7da3-4eb2-a62c-469fbe436280",
      "rating": 1,
      "review_text": "very high brokerage not best option",
      "review_date": "2026-03-12 05:18:27"
    },
    {
      "reviewId": "9e25f367-5cb8-4f9a-9720-ad186ff6d710",
      "rating": 4,
      "review_text": "Hello Groww Team, Your app is very nice and easy to use for Demat accounts, trading, and mutual fund investments. However, compared to some other trading apps like some trading charts, settings, and trading map features are better there. I have one suggestion for improvement in the Groww app. In the mutual fund section, it would be very helpful if you show how many people are investing in each fund and how much money investors have invested in that fund. This will help users popular funds.😢😂❤",
      "review_date": "2026-03-12 04:20:36"
    },
    {
      "reviewId": "c7f5f82b-549c-4ad8-81af-a4ac1a1ba631",
      "rating": 5,
      "review_text": "Groww app is the best Stock Plateform of all Company Details on the available Groww platform. ✅This platform is good for the futures.",
      "review_date": "2026-03-12 02:21:33"
    },
    {
      "reviewId": "d2c1bd1f-8b94-4804-bbb1-0a8250b5b173",
      "rating": 4,
      "review_text": "Super app with zero AMC charges. But I have only one suggestion, please provide an option to buy stocks on the basis of amount. It only shows quantity, converting into amount takes time and makes some user confused on the conversion. so please work on this to provide 'Amount option while buying stocks'",
      "review_date": "2026-03-11 23:46:05"
    },
    {
      "reviewId": "25853e8a-b6d5-4c70-9487-9507f1597f5b",
      "rating": 5,
      "review_text": "very help fully app I'm very happy 😊",
      "review_date": "2026-03-11 22:16:37"
    },
    {
      "reviewId": "35e17b01-3d44-45d1-839a-9f40d974c3ad",
      "rating": 5,
      "review_text": "great app experience but brokerage thoda jyada h",
      "review_date": "2026-03-11 20:21:19"
    },
    {
      "reviewId": "824ceb72-8909-43a5-8299-2b0e4e50f46c",
      "rating": 2,
      "review_text": "order get canceled with out reason in intraday if delivery was taken at 11 am in morning no reason anything and also autopay will be added of any amount without consent some time seems like scan. please watch out for autopay if not active might be 15k auto can be added automatically.",
      "review_date": "2026-03-11 20:08:04"
    },
    {
      "reviewId": "5e263830-47ce-4b0a-80dd-d94506c6c7e5",
      "rating": 1,
      "review_text": "worst experience in Groww app. Poor customer care service.",
      "review_date": "2026-03-11 19:03:34"
    },
    {
      "reviewId": "d8d95bc5-0f93-43a5-be82-b7f6ed576c5e",
      "rating": 5,
      "review_text": "its very user friendly no doubt.My suggestions are -1* Looking at one's portfolio ,loss making stocks, when to exit & for new purchase when to opt.In this era of on-line fraud its difficult to identify the fraudsters so request.2* Long term large cap,mid- cap & small if individual personalised advice ,of course ,I don't mean free of cost but you can charge me but it is reliable, authentic & trustworthy.As the study of stocks, technical ,fundamental ,have done but still no clear cut idea.",
      "review_date": "2026-03-11 18:49:04"
    },
    {
      "reviewId": "aa017dbd-ccc8-4cc4-ab2a-adc8cb6ed223",
      "rating": 1,
      "review_text": "Trust me App Sucks I made my account in Groww For Sips but there's a message always shows me something went wrong please try again later fix this disgusting issue please",
      "review_date": "2026-03-11 18:25:51"
    },
    {
      "reviewId": "be43efd8-68fa-49e8-8e77-4aff94eb1734",
      "rating": 1,
      "review_text": "Worst Investment, Mutual Funds Platform Ever.",
      "review_date": "2026-03-11 17:57:09"
    },
    {
      "reviewId": "98d56306-76a6-47a4-93cf-d93cd42daa80",
      "rating": 3,
      "review_text": "MTf charges are high compared to other brokers minor bugs",
      "review_date": "2026-03-11 16:09:01"
    },
    {
      "reviewId": "60c954bb-fce6-4048-b1f2-06bca4f7e198",
      "rating": 5,
      "review_text": "The indias biggest broker",
      "review_date": "2026-03-11 15:56:52"
    },
    {
      "reviewId": "4d8f142e-671e-4efd-afa7-341e9fa0be92",
      "rating": 5,
      "review_text": "my sher. long time 3 years good shees",
      "review_date": "2026-03-11 15:48:17"
    },
    {
      "reviewId": "400fbb25-f8fe-46f0-a79b-5f4724d207b9",
      "rating": 1,
      "review_text": "frud app hai charges pahle karleta hai aur profit jitna hai utna nhi bhejta mat dounload karo",
      "review_date": "2026-03-11 15:22:31"
    },
    {
      "reviewId": "5140e7d9-b7ae-46b8-bb4d-0f45d3e7fdc3",
      "rating": 1,
      "review_text": "very low my amount in last 1 year , mid cap investment",
      "review_date": "2026-03-11 15:05:58"
    },
    {
      "reviewId": "c470c19b-8b4e-47f9-b9c7-e639dbf4db18",
      "rating": 1,
      "review_text": "Date=11-03-2026 Sensex 12 march 77500 put Buy Entry price=627.60=12:54 pm Stop Loss=593.60=1:00 pm Target Price=777 1:00 pm candle low price is 596.70 than how can my stop loss hit??? And after that 1:17 Candle my target hit 777 Rs 2988 Rs And Groww close my trade At -689 Rs I want refund of my profitable Trade 2988 Rs in my demat ac or my bank ac.. If groww app you are not fraud than refund my profitable trade 2988 Rs please..If refund come in my account than i will delete this negetive review",
      "review_date": "2026-03-11 14:18:12"
    },
    {
      "reviewId": "baac2506-c8c1-4c31-8883-f8d96775553f",
      "rating": 5,
      "review_text": "I can't login to my account.",
      "review_date": "2026-03-11 13:12:34"
    },
    {
      "reviewId": "06c18faa-97fe-48ef-b0f7-4101ae3b9dda",
      "rating": 4,
      "review_text": "It's unable to import external funds from the past 10 days. Why? is there any issue? If so, is there any ETR? And we dont have any complaints or escalation mechanisms in the app, please provide these.",
      "review_date": "2026-03-11 12:23:42"
    },
    {
      "reviewId": "c2c45aa4-0460-4480-b356-33c714cb5a0b",
      "rating": 1,
      "review_text": "i don't understand why the external funds tracking is currently not available, I have already contacted the support team on it but still no update",
      "review_date": "2026-03-11 12:06:09"
    },
    {
      "reviewId": "069d19b9-abb7-448f-9bb7-e77d84caa076",
      "rating": 5,
      "review_text": "grow🥲🥲5 star.....please add the double scree and trepple screen option ....kyoki esase user ko asaani hogi tred karne me...ek hi scree par call and put ko aad karke aasani se trede kar skta he. dhanwaad🎈🎈",
      "review_date": "2026-03-11 11:38:56"
    },
    {
      "reviewId": "4efb4cd0-8b5e-48e7-af22-905acb7d15c1",
      "rating": 1,
      "review_text": "wrong experience",
      "review_date": "2026-03-11 11:06:06"
    },
    {
      "reviewId": "be595fb4-304a-449f-9991-2b2936a4db83",
      "rating": 1,
      "review_text": "Biggest Crashed Application ever i have seen, not even a single chart is opening how to enter or exit..i strongly recommend to go with other standard brokers..",
      "review_date": "2026-03-11 10:31:32"
    },
    {
      "reviewId": "e462eef4-3b5f-4e14-be68-8b315d01962e",
      "rating": 5,
      "review_text": "superb app but sometimes(in fact many times) the order limit price doesn't reflect in order, I think we need to refresh multiple times and many times we need to close the app and again need to start to see the modify price, please improve this, In fact the game is all about ordering. Thank you",
      "review_date": "2026-03-11 10:31:12"
    },
    {
      "reviewId": "886c4216-4000-4efe-8133-460306878917",
      "rating": 5,
      "review_text": "mutual fund holding not refreshing.... please do the needful",
      "review_date": "2026-03-11 09:58:34"
    },
    {
      "reviewId": "a183c06d-189d-42b8-87e3-f0d682ffe029",
      "rating": 4,
      "review_text": "previous update used to have a feature in which we can watch multiple charts at a time and now it's gone",
      "review_date": "2026-03-11 09:49:38"
    },
    {
      "reviewId": "43c9c265-09c4-42d5-b04e-088a2e7276e2",
      "rating": 2,
      "review_text": "Nifty index Chart par volume show nahi hota Trading view ki tarah tool bhi save nahi hote please add these features",
      "review_date": "2026-03-11 09:32:59"
    },
    {
      "reviewId": "b6dd3472-6654-4074-aabd-ae506cf61da5",
      "rating": 1,
      "review_text": "worst app, not loading",
      "review_date": "2026-03-11 09:23:29"
    },
    {
      "reviewId": "9dd16e82-4525-46f3-a23b-b3bb3d254e35",
      "rating": 1,
      "review_text": "One of the most worst app. The brokerage charges too high and I suggest don't use this app.",
      "review_date": "2026-03-11 07:30:40"
    },
    {
      "reviewId": "37c90efb-2aa3-4b70-9ee1-f0b09f90c9e2",
      "rating": 1,
      "review_text": "External fund import is failing. Kindly fix the Customer will choose better option.",
      "review_date": "2026-03-11 06:28:17"
    },
    {
      "reviewId": "5d24d351-0a13-4a26-a3eb-8a458c0cdcce",
      "rating": 1,
      "review_text": "External fund Import has not been working since last 2 weeks but Groww did not help to resolve it. Timely updation of units of new purchase is very poor, since they stop Import fund from MF CENTRAL.",
      "review_date": "2026-03-11 03:16:20"
    },
    {
      "reviewId": "53b03d07-4c44-48ac-99da-08f4e5713342",
      "rating": 1,
      "review_text": "not able to refresh the external fund , earlier used to refresh but recently that feature is decomposed.",
      "review_date": "2026-03-11 00:18:19"
    },
    {
      "reviewId": "b474f139-2619-4131-bb1d-d130a7d18969",
      "rating": 1,
      "review_text": "I don't know why groww removed for external mutual funds from showing in the app",
      "review_date": "2026-03-11 00:12:01"
    },
    {
      "reviewId": "4cd0a188-ace4-49ce-9684-cb8fb1e692d8",
      "rating": 1,
      "review_text": "loote chhe users ne charges thi",
      "review_date": "2026-03-10 22:43:43"
    }
  ]
}